lime_solo_int01/__init__.py
lime_solo_int01/core.py
lime_solo_int01-0.0.1.dist-info/METADATA
lime_solo_int01-0.0.1.dist-info/WHEEL
lime_solo_int01-0.0.1.dist-info/top_level.txt
lime_solo_int01-0.0.1.dist-info/RECORD
