Metadata-Version: 2.4
Name: lime-solo-int01
Version: 0.0.1
Summary: package works
Author: lime
License: MIT
Requires-Python: >=3.8
